{
  "gold": {
    "exporters": ["mercury", "earth", "ganymede", "titan"],
    "importers": ["pluto", "ceres", "europa", "venus", "mars"],
    "price": 40.29,
    "unit": "kg",
    "lower bound": 140,
    "upper bound": 220
  },

  "iron": {
    "exporters": ["mars", "earth", "callisto", "rhea", "enceladus", "neptune", "ceres"],
    "importers": ["the moon", "uranus", "io", "pluto"],
    "price": 3,
    "unit": "kg",
    "lower bound": 250,
    "upper bound": 1000
  },

  "helium-3": {
    "exporters": ["jupiter", "saturn", "neptune", "venus"],
    "importers": ["eris", "earth", "europa", "mercury", "ganymede"],
    "price": 2290,
    "unit": "g",
    "lower bound": 1,
    "upper bound": 5
  },

  "carbon": {
    "exporters": ["triton", "pluto", "venus", "saturn", "eris"],
    "importers": ["mars", "titan", "iapetus", "ceres", "rhea"],
    "price": 4.6,
    "unit": "kg",
    "lower bound": 540,
    "upper bound": 670
  },

  "silicon": {
    "exporters": ["the moon", "enceladus", "uranus", "io", "ganymede"],
    "importers": ["mercury", "ganymede", "callisto", "triton", "titan"],
    "price": 2,
    "unit": "kg",
    "lower bound": 302,
    "upper bound": 1409
  },

  "water": {
    "exporters": ["neptune", "europa", "earth", "enceladus", "iapetus"],
    "importers": ["mars", "the moon", "triton", "io", "ganymede", "saturn", "eris"],
    "price": 0.8,
    "unit": "kg",
    "lower bound": 300,
    "upper bound": 1200
  }
}
